namegiver/__init__.py
namegiver/namegiver.py
namegiver-0.1.4.dist-info/LICENSE
namegiver-0.1.4.dist-info/METADATA
namegiver-0.1.4.dist-info/WHEEL
namegiver-0.1.4.dist-info/entry_points.txt
namegiver-0.1.4.dist-info/top_level.txt
namegiver-0.1.4.dist-info/RECORD
