Metadata-Version: 2.2
Name: namegiver
Version: 0.1.4
Summary: AI-based Character Name Generator
Home-page: https://github.com/masked-fox-productions/namegiver
Author: Aaron Pogue
Author-email: aaron.pogue@maskedfox.com
Classifier: Programming Language :: Python :: 3
Classifier: License :: OSI Approved :: MIT License
Classifier: Operating System :: OS Independent
Requires-Python: >=3.6
License-File: LICENSE
Requires-Dist: openai
Requires-Dist: python-dotenv
Requires-Dist: python-Levenshtein
Dynamic: author
Dynamic: author-email
Dynamic: classifier
Dynamic: description
Dynamic: description-content-type
Dynamic: home-page
Dynamic: requires-dist
Dynamic: requires-python
Dynamic: summary
